aws_prototyping_sdk/type_safe_api/__init__.py
aws_prototyping_sdk/type_safe_api/py.typed
aws_prototyping_sdk/type_safe_api/_jsii/__init__.py
aws_prototyping_sdk/type_safe_api/_jsii/type-safe-api@0.19.68.jsii.tgz
aws_prototyping_sdk.type_safe_api-0.19.68.data/scripts/clean-openapi-generated-code
aws_prototyping_sdk.type_safe_api-0.19.68.data/scripts/copy-gradle-wrapper
aws_prototyping_sdk.type_safe_api-0.19.68.data/scripts/generate
aws_prototyping_sdk.type_safe_api-0.19.68.data/scripts/generate-html-redoc-docs
aws_prototyping_sdk.type_safe_api-0.19.68.data/scripts/generate-mock-data
aws_prototyping_sdk.type_safe_api-0.19.68.data/scripts/parse-openapi-spec
aws_prototyping_sdk.type_safe_api-0.19.68.dist-info/LICENSE
aws_prototyping_sdk.type_safe_api-0.19.68.dist-info/METADATA
aws_prototyping_sdk.type_safe_api-0.19.68.dist-info/WHEEL
aws_prototyping_sdk.type_safe_api-0.19.68.dist-info/top_level.txt
aws_prototyping_sdk.type_safe_api-0.19.68.dist-info/RECORD
