Metadata-Version: 2.1
Name: aws-prototyping-sdk.type-safe-api
Version: 0.19.68
Summary: @aws-prototyping-sdk/type-safe-api
Home-page: https://github.com/aws/aws-prototyping-sdk
Author: AWS APJ COPE<apj-cope@amazon.com>
License: Apache-2.0
Project-URL: Source, https://github.com/aws/aws-prototyping-sdk
Platform: UNKNOWN
Classifier: Intended Audience :: Developers
Classifier: Operating System :: OS Independent
Classifier: Programming Language :: JavaScript
Classifier: Programming Language :: Python :: 3 :: Only
Classifier: Programming Language :: Python :: 3.7
Classifier: Programming Language :: Python :: 3.8
Classifier: Programming Language :: Python :: 3.9
Classifier: Programming Language :: Python :: 3.10
Classifier: Programming Language :: Python :: 3.11
Classifier: Typing :: Typed
Classifier: Development Status :: 4 - Beta
Classifier: License :: OSI Approved
Requires-Python: ~=3.7
License-File: LICENSE
Requires-Dist: aws-cdk-lib (<3.0.0,>=2.81.0)
Requires-Dist: aws-prototyping-sdk.nx-monorepo (<1.0.0)
Requires-Dist: aws-prototyping-sdk.pdk-nag (<1.0.0)
Requires-Dist: cdk-nag (<3.0.0,>=2.27.24)
Requires-Dist: constructs (<11.0.0,>=10.2.39)
Requires-Dist: jsii (<2.0.0,>=1.82.0)
Requires-Dist: projen (<0.72.0,>=0.71.92)
Requires-Dist: publication (>=0.0.3)
Requires-Dist: typeguard (~=2.13.3)
